chcats/__init__.py
chcats/chcats.py
chinilla_CAT_admin-1.0.0.dist-info/LICENSE
chinilla_CAT_admin-1.0.0.dist-info/METADATA
chinilla_CAT_admin-1.0.0.dist-info/WHEEL
chinilla_CAT_admin-1.0.0.dist-info/entry_points.txt
chinilla_CAT_admin-1.0.0.dist-info/top_level.txt
chinilla_CAT_admin-1.0.0.dist-info/RECORD
